httprest/__init__.py
httprest/api.py
httprest/http/__init__.py
httprest/http/auth.py
httprest/http/base.py
httprest/http/cert.py
httprest/http/errors.py
httprest/http/fake_client.py
httprest/http/requests_client.py
httprest/http/response.py
httprest/http/timeout.py
httprest/http/urllib_client.py
httprest-0.4.1.dist-info/METADATA
httprest-0.4.1.dist-info/WHEEL
httprest-0.4.1.dist-info/licenses/LICENSE
httprest-0.4.1.dist-info/RECORD
