Metadata-Version: 2.4
Name: httprest
Version: 0.4.1
Summary: A library for making simple REST-like HTTP requests
License: MIT
License-File: LICENSE
Author: Andrii Nechaiev
Author-email: andrewnech@gmail.com
Requires-Python: >=3.9,<4.0
Classifier: Development Status :: 4 - Beta
Classifier: Intended Audience :: Developers
Classifier: License :: OSI Approved :: MIT License
Classifier: Operating System :: POSIX :: Linux
Classifier: Programming Language :: Python
Classifier: Programming Language :: Python :: 3
Classifier: Programming Language :: Python :: 3.9
Classifier: Programming Language :: Python :: 3.10
Classifier: Programming Language :: Python :: 3.11
Classifier: Programming Language :: Python :: 3.12
Classifier: Programming Language :: Python :: 3.13
Classifier: Programming Language :: Python :: 3.14
Classifier: Programming Language :: Python :: 3 :: Only
Classifier: Programming Language :: Python :: Implementation :: CPython
Classifier: Topic :: Software Development :: Libraries
Classifier: Topic :: Utilities
Provides-Extra: requests-client
Requires-Dist: requests (>=2.32.3,<3.0.0) ; extra == "requests-client"
Project-URL: Repository, https://github.com/litteratum/httprest
